parsival/__init__.py
parsival/helper_rules.py
parsival/peg_grammar.py
parsival/scripts/grammar_generator/__main__.py
parsival/scripts/grammar_generator/custom_indent.py
parsival/scripts/grammar_generator/gram_to_py.py
parsival/scripts/grammar_generator/postprocess.py
parsival-0.0.0a3.dist-info/LICENSE
parsival-0.0.0a3.dist-info/METADATA
parsival-0.0.0a3.dist-info/WHEEL
parsival-0.0.0a3.dist-info/entry_points.txt
parsival-0.0.0a3.dist-info/top_level.txt
parsival-0.0.0a3.dist-info/RECORD
