Metadata-Version: 2.1
Name: parsival
Version: 0.0.0a3
Summary: A class-based language parser.
Author: AbyxDev
License: GNU LESSER GENERAL PUBLIC LICENSE
Project-URL: Source, https://github.com/Kenny2github/parsival
Keywords: parser,grammar,language
Classifier: Development Status :: 3 - Alpha
Classifier: Intended Audience :: Developers
Classifier: Topic :: Software Development :: Compilers
Classifier: Topic :: Software Development :: Interpreters
Classifier: Topic :: Text Processing :: General
Classifier: License :: OSI Approved :: GNU Lesser General Public License v3 or later (LGPLv3+)
Classifier: Programming Language :: Python :: 3
Classifier: Programming Language :: Python :: 3 :: Only
Classifier: Programming Language :: Python :: 3.9
Classifier: Typing :: Typed
Requires-Python: >=3.9
License-File: LICENSE
Provides-Extra: docs
Requires-Dist: sphinx ; extra == 'docs'
Requires-Dist: furo ; extra == 'docs'
Provides-Extra: test
Requires-Dist: pytest ; extra == 'test'
